binance_sdk_ebate/__init__.py
binance_sdk_ebate/client.py
binance_sdk_ebate-10.0.0.dist-info/licenses/LICENSE
binance_sdk_ebate-10.0.0.dist-info/METADATA
binance_sdk_ebate-10.0.0.dist-info/WHEEL
binance_sdk_ebate-10.0.0.dist-info/top_level.txt
binance_sdk_ebate-10.0.0.dist-info/RECORD
