Metadata-Version: 2.4
Name: binance-sdk-ebate
Version: 10.0.0
Summary: Demo SDK for Binance rebate migration testing (safe PoC)
Home-page: https://github.com/binance/binance-connector-python/blob/f1703c54c3059423a8568b2300597210b19b938e/clients/rebate/docs/migration_guide_rebate_sdk.md
Author: TitifelBro47
Author-email: titifel@example.com
Classifier: Programming Language :: Python :: 3
Classifier: License :: OSI Approved :: MIT License
Classifier: Operating System :: OS Independent
Requires-Python: >=3.8
License-File: LICENSE
Requires-Dist: requests
Dynamic: author
Dynamic: author-email
Dynamic: classifier
Dynamic: description
Dynamic: description-content-type
Dynamic: home-page
Dynamic: license-file
Dynamic: requires-dist
Dynamic: requires-python
Dynamic: summary
